README.md
setup.py
bin/ycat
ycat/__init__.py
ycat.egg-info/PKG-INFO
ycat.egg-info/SOURCES.txt
ycat.egg-info/dependency_links.txt
ycat.egg-info/top_level.txt
ycat.egg-info/zip-safe