Metadata-Version: 2.1
Name: ycat
Version: 1
Summary: display yaml in flat format
Home-page: https://git.osuv.de/m/ycat
Author: Markus Bergholz
Author-email: markuman@gmail.com  
License: WTFPL
Platform: UNKNOWN
